s3_sysbackup/__init__.py
s3_sysbackup/__main__.py
s3_sysbackup/cf_setup.py
s3_sysbackup/fs.py
s3_sysbackup/program.py
s3_sysbackup/quilting.py
s3_sysbackup/resource_setup.py
s3_sysbackup/saver.py
s3_sysbackup/snapshots.py
s3_sysbackup/system_setup.py
s3_sysbackup/utils.py
s3_sysbackup/version.py
s3_sysbackup/cf_templates/createuser.yml
s3_sysbackup/cf_templates/prev-resources.yml
s3_sysbackup/cf_templates/resources.yml
s3_sysbackup/systemd_templates/archive.service
s3_sysbackup/systemd_templates/archive.timer
s3_sysbackup-0.2.0.dist-info/LICENSE
s3_sysbackup-0.2.0.dist-info/METADATA
s3_sysbackup-0.2.0.dist-info/WHEEL
s3_sysbackup-0.2.0.dist-info/entry_points.txt
s3_sysbackup-0.2.0.dist-info/top_level.txt
s3_sysbackup-0.2.0.dist-info/RECORD
