Metadata-Version: 2.1
Name: s3-sysbackup
Version: 0.2.0
Summary: A flexible, Unix-philosophy backup utility saving to AWS S3 WORM storage
Home-page: https://github.com/rtweeks/s3-sysbackup
Author: Richard T. Weeks
Author-email: rtweeks21@gmail.com
License: UNKNOWN
Project-URL: Bug Tracker, https://github.com/rtweeks/s3-sysbackup/issues
Platform: UNKNOWN
Classifier: Programming Language :: Python :: 3
Classifier: License :: OSI Approved :: GNU General Public License v3 or later (GPLv3+)
Classifier: Operating System :: POSIX :: Linux
Classifier: Topic :: System :: Archiving :: Backup
Requires-Python: >=3.6
License-File: LICENSE
Requires-Dist: boto3
Requires-Dist: ansicolors (~=1.1)
